{"skeleton":{"hash":"d39/0bAPOm90s4hs0qFn6TGE0nI","spine":"3.7.94","width":245,"height":274,"images":"./ship/","audio":"/Users/dat09/Desktop/PIRATE KING"},"bones":[{"name":"root"},{"name":"scale","parent":"root"},{"name":"ship","parent":"scale"},{"name":"explode","parent":"root"},{"name":"explode ship","parent":"root"},{"name":"bot","parent":"explode ship"},{"name":"mid","parent":"explode ship"},{"name":"top","parent":"explode ship"},{"name":"b1","parent":"bot"},{"name":"b2","parent":"bot"},{"name":"b3","parent":"bot"},{"name":"b4","parent":"bot"},{"name":"b5","parent":"bot"},{"name":"b6","parent":"bot"},{"name":"m1","parent":"mid"},{"name":"m2","parent":"mid"},{"name":"m3","parent":"mid"},{"name":"t1","parent":"top"},{"name":"t2","parent":"top"},{"name":"t3","parent":"top"},{"name":"water","parent":"explode ship"},{"name":"Result","parent":"root"},{"name":"Win","parent":"Result"},{"name":"lose","parent":"Result"},{"name":"light","parent":"Result"},{"name":"Wave","parent":"root","y":-10.8}],"slots":[{"name":"ship_outerglow","bone":"ship","attachment":"ship_outerglow"},{"name":"explode ship/water","bone":"water","attachment":"explode ship/water"},{"name":"bot5","bone":"b5","attachment":"explode ship/bot/bot 5"},{"name":"bot4","bone":"b4","attachment":"explode ship/bot/bot 4"},{"name":"bot6","bone":"b6","attachment":"explode ship/bot/bot6"},{"name":"mid 1","bone":"m1","attachment":"explode ship/mid/mid 1"},{"name":"mid2","bone":"m2","attachment":"explode ship/mid/mid 2"},{"name":"mid3","bone":"m3","attachment":"explode ship/mid/mid 3"},{"name":"top1","bone":"t1","attachment":"explode ship/top/top 1"},{"name":"top2","bone":"t2","attachment":"explode ship/top/top2"},{"name":"top3","bone":"t3","attachment":"explode ship/top/top3"},{"name":"bot3","bone":"b3","attachment":"explode ship/bot/bot 3"},{"name":"bot2","bone":"b2","attachment":"explode ship/bot/bot 2"},{"name":"bot1","bone":"b1","attachment":"explode ship/bot/bot 1"},{"name":"reasure & Skull/light 101","bone":"light"},{"name":"reasure & Skull/skull","bone":"lose"},{"name":"treasure & Skull/treasure","bone":"Win"},{"name":"explode/2","bone":"explode"},{"name":"Wave","bone":"Wave","attachment":"wave/1"},{"name":"wave/1","bone":"Wave"},{"name":"wave/2","bone":"Wave"},{"name":"wave/3","bone":"Wave"},{"name":"wave/4","bone":"Wave"},{"name":"wave/6","bone":"Wave"},{"name":"wave/7","bone":"Wave"},{"name":"wave/8","bone":"Wave"},{"name":"wave/9","bone":"Wave"},{"name":"ship","bone":"ship","attachment":"wave/ship 1"}],"skins":{"default":{"Wave":{"wave/1":{"x":0.5,"y":-76.02,"width":223,"height":77}},"bot1":{"explode ship/bot/bot 1":{"x":-21.96,"y":-38.11,"width":41,"height":91}},"bot2":{"explode ship/bot/bot 2":{"x":8.27,"y":-66.48,"width":48,"height":47}},"bot3":{"explode ship/bot/bot 3":{"x":32.81,"y":-55.84,"width":37,"height":63}},"bot4":{"explode ship/bot/bot 4":{"x":38.61,"y":-44.92,"width":66,"height":60}},"bot5":{"explode ship/bot/bot 5":{"x":66.59,"y":-10.53,"width":20,"height":63}},"bot6":{"explode ship/bot/bot6":{"x":8.27,"y":-37.43,"width":42,"height":30}},"explode ship/water":{"explode ship/water":{"x":9.5,"y":-78,"width":220,"height":116}},"explode/2":{"explode/2":{"y":-47,"width":86,"height":90},"explode/3":{"y":-47,"width":100,"height":92},"explode/4":{"y":-47,"width":146,"height":107},"explode/5":{"y":-25,"width":160,"height":143},"explode/6":{"x":22,"y":-22,"width":247,"height":189},"explode/7":{"x":18,"y":-8,"width":257,"height":218},"explode/8":{"x":1.5,"y":-0.5,"width":293,"height":233}},"mid 1":{"explode ship/mid/mid 1":{"x":18.62,"y":20.59,"width":167,"height":119}},"mid2":{"explode ship/mid/mid 2":{"x":20.09,"y":19.02,"width":163,"height":116}},"mid3":{"explode ship/mid/mid 3":{"x":-20.38,"y":20.88,"width":81,"height":94}},"reasure & Skull/light 101":{"treasure & Skull/light 100":{"width":239,"height":240}},"reasure & Skull/skull":{"treasure & Skull/skull":{"width":92,"height":132}},"ship":{"wave/ship 1":{"x":0.5,"width":241,"height":274}},"ship_outerglow":{"ship_outerglow":{"width":245,"height":274}},"top1":{"explode ship/top/top 1":{"x":9.85,"y":71.71,"width":74,"height":58}},"top2":{"explode ship/top/top2":{"x":26,"y":60.39,"width":42,"height":35}},"top3":{"explode ship/top/top3":{"x":2.36,"y":80.38,"width":60,"height":42}},"treasure & Skull/treasure":{"treasure & Skull/treasure":{"y":0.5,"width":220,"height":207}},"wave/1":{"wave/2":{"x":0.5,"y":-76.02,"width":215,"height":80}},"wave/2":{"wave/3":{"x":0.5,"y":-76.52,"width":217,"height":88}},"wave/3":{"wave/4":{"x":0.5,"y":-76.02,"width":233,"height":95}},"wave/4":{"wave/5":{"x":0.5,"y":-72.8,"width":232,"height":99}},"wave/6":{"wave/6":{"x":12,"y":-66.31,"width":227,"height":92}},"wave/7":{"wave/7":{"x":4.29,"y":-66.42,"width":247,"height":90}},"wave/8":{"wave/8":{"x":13.43,"y":-67.91,"width":245,"height":91}},"wave/9":{"wave/9":{"x":13.43,"y":-71.88,"width":264,"height":81}}}},"animations":{"action_lose":{"slots":{"Wave":{"attachment":[{"time":0,"name":null}]},"bot1":{"color":[{"time":0.6,"color":"ffffffff"},{"time":0.7,"color":"ffffff00"}],"attachment":[{"time":0,"name":null},{"time":0.1,"name":"explode ship/bot/bot 1"},{"time":0.7333,"name":null}]},"bot2":{"color":[{"time":0.6,"color":"ffffffff"},{"time":0.7,"color":"ffffff00"}],"attachment":[{"time":0,"name":null},{"time":0.1,"name":"explode ship/bot/bot 2"},{"time":0.7333,"name":null}]},"bot3":{"color":[{"time":0.6,"color":"ffffffff"},{"time":0.7,"color":"ffffff00"}],"attachment":[{"time":0,"name":null},{"time":0.1,"name":"explode ship/bot/bot 3"},{"time":0.7333,"name":null}]},"bot4":{"color":[{"time":0.6,"color":"ffffffff"},{"time":0.7,"color":"ffffff00"}],"attachment":[{"time":0,"name":null},{"time":0.1,"name":"explode ship/bot/bot 4"},{"time":0.7333,"name":null}]},"bot5":{"color":[{"time":0.6,"color":"ffffffff"},{"time":0.7,"color":"ffffff00"}],"attachment":[{"time":0,"name":null},{"time":0.1,"name":"explode ship/bot/bot 5"},{"time":0.7333,"name":null}]},"bot6":{"color":[{"time":0.6,"color":"ffffffff"},{"time":0.7,"color":"ffffff00"}],"attachment":[{"time":0,"name":null},{"time":0.1,"name":"explode ship/bot/bot6"},{"time":0.7333,"name":null}]},"explode ship/water":{"color":[{"time":0.6,"color":"ffffffff"},{"time":0.7,"color":"ffffff00"}],"attachment":[{"time":0,"name":null},{"time":0.1,"name":"explode ship/water"},{"time":0.7333,"name":null}]},"explode/2":{"color":[{"time":0.6,"color":"ffffffff"},{"time":0.7,"color":"ffffff00"}],"attachment":[{"time":0.1,"name":"explode/2"},{"time":0.2,"name":"explode/3"},{"time":0.2667,"name":"explode/4"},{"time":0.3333,"name":"explode/5"},{"time":0.4333,"name":"explode/6"},{"time":0.5,"name":"explode/7"},{"time":0.6,"name":"explode/8"},{"time":0.7333,"name":null}]},"mid2":{"color":[{"time":0.6,"color":"ffffffff"},{"time":0.7,"color":"ffffff00"}],"attachment":[{"time":0,"name":null},{"time":0.3333,"name":"explode ship/mid/mid 2"},{"time":0.7333,"name":null}]},"mid3":{"color":[{"time":0.6,"color":"ffffffff"},{"time":0.7,"color":"ffffff00"}],"attachment":[{"time":0,"name":null},{"time":0.3333,"name":"explode ship/mid/mid 3"},{"time":0.7333,"name":null}]},"mid 1":{"attachment":[{"time":0,"name":null},{"time":0.1,"name":"explode ship/mid/mid 1"},{"time":0.3333,"name":null}]},"reasure & Skull/skull":{"attachment":[{"time":0.6333,"name":"treasure & Skull/skull"}]},"ship":{"attachment":[{"time":0,"name":null}]},"ship_outerglow":{"attachment":[{"time":0.1,"name":null}]},"top1":{"attachment":[{"time":0,"name":null},{"time":0.1,"name":"explode ship/top/top 1"},{"time":0.2667,"name":null}]},"top2":{"color":[{"time":0.6,"color":"ffffffff"},{"time":0.7,"color":"ffffff00"}],"attachment":[{"time":0,"name":null},{"time":0.2667,"name":"explode ship/top/top2"},{"time":0.7333,"name":null}]},"top3":{"color":[{"time":0.6,"color":"ffffffff"},{"time":0.7,"color":"ffffff00"}],"attachment":[{"time":0,"name":null},{"time":0.2667,"name":"explode ship/top/top3"},{"time":0.7333,"name":null}]}},"bones":{"explode":{"scale":[{"time":0.6,"x":1,"y":1},{"time":0.7,"x":1.2,"y":1.2}]},"b6":{"rotate":[{"time":0.1,"angle":0},{"time":0.4,"angle":107.62},{"time":0.6,"angle":-150}],"translate":[{"time":0.1,"x":0,"y":0},{"time":0.4,"x":-76.01,"y":-41.32},{"time":0.7,"x":-181.24,"y":-78.08}],"shear":[{"time":0.1,"x":0,"y":0},{"time":0.4,"x":90,"y":75},{"time":0.7,"x":0,"y":-180}]},"b1":{"rotate":[{"time":0.1,"angle":0},{"time":0.2667,"angle":15},{"time":0.3333,"angle":30},{"time":0.4333,"angle":45,"curve":"stepped"},{"time":0.6,"angle":45},{"time":0.7,"angle":60}],"translate":[{"time":0.1,"x":0,"y":0},{"time":0.2,"x":-19.1,"y":-0.5},{"time":0.2667,"x":-47.99,"y":-2.51},{"time":0.3333,"x":-77.12,"y":-6.42},{"time":0.4333,"x":-113.14,"y":-7.07},{"time":0.5,"x":-125.87,"y":-8.49,"curve":"stepped"},{"time":0.6,"x":-125.87,"y":-8.49},{"time":0.7,"x":-148.61,"y":-108.15}],"scale":[{"time":0.1,"x":1,"y":1},{"time":0.3333,"x":0.803,"y":1},{"time":0.5,"x":0.671,"y":1}],"shear":[{"time":0.3333,"x":0,"y":0},{"time":0.4333,"x":-143.64,"y":0},{"time":0.7,"x":-36.52,"y":0}]},"b2":{"rotate":[{"time":0.1,"angle":0},{"time":0.2,"angle":-5},{"time":0.2667,"angle":-30},{"time":0.3333,"angle":-60},{"time":0.4333,"angle":-75}],"translate":[{"time":0.1,"x":0,"y":0},{"time":0.2,"x":14.47,"y":4.76},{"time":0.2667,"x":89.95,"y":5.8},{"time":0.3333,"x":130.93,"y":-2.47},{"time":0.4333,"x":174.68,"y":-7.06},{"time":0.7,"x":175.92,"y":15.65}],"scale":[{"time":0.1,"x":1,"y":1},{"time":0.7,"x":0.5,"y":0.5}],"shear":[{"time":0.1,"x":0,"y":0},{"time":0.3333,"x":-180,"y":0},{"time":0.7,"x":135,"y":0}]},"b3":{"rotate":[{"time":0.1,"angle":0},{"time":0.2,"angle":-15},{"time":0.2667,"angle":-45},{"time":0.3333,"angle":-65}],"translate":[{"time":0.1,"x":0,"y":0},{"time":0.2,"x":17.59,"y":7.71},{"time":0.2667,"x":64.35,"y":12.02},{"time":0.3333,"x":113.09,"y":-3.54},{"time":0.4333,"x":133.51,"y":-9.46},{"time":0.5,"x":145.88,"y":-11.21},{"time":0.7,"x":125.81,"y":-40.42}],"scale":[{"time":0.1,"x":1,"y":1},{"time":0.7,"x":0.3,"y":0.3}]},"b4":{"rotate":[{"time":0.1,"angle":0},{"time":0.2667,"angle":12.07},{"time":0.6,"angle":75}],"translate":[{"time":0.1,"x":0.76,"y":1.52},{"time":0.7,"x":132.36,"y":-29.49}],"shear":[{"time":0.1,"x":0,"y":0},{"time":0.7,"x":145,"y":0}]},"b5":{"rotate":[{"time":0.4,"angle":0},{"time":0.6,"angle":-46.5}],"translate":[{"time":0.4,"x":0,"y":0},{"time":0.6,"x":50.92,"y":39.52},{"time":0.7,"x":72.24,"y":24.63}]},"m1":{"rotate":[{"time":0.2,"angle":5}],"translate":[{"time":0.2,"x":0,"y":8}]},"m2":{"rotate":[{"time":0.2,"angle":0},{"time":0.3333,"angle":15},{"time":0.4333,"angle":30},{"time":0.6,"angle":-54.02},{"time":0.7,"angle":-65}],"translate":[{"time":0.2,"x":0,"y":0},{"time":0.3333,"x":10,"y":20},{"time":0.4333,"x":45.88,"y":32.15},{"time":0.5,"x":61.14,"y":66.03},{"time":0.6,"x":90.06,"y":75.32},{"time":0.7,"x":117.51,"y":27.21}],"scale":[{"time":0.2,"x":1,"y":1},{"time":0.6,"x":1.5,"y":0.6}],"shear":[{"time":0.2,"x":0,"y":0},{"time":0.7,"x":0,"y":-45}]},"m3":{"rotate":[{"time":0.2,"angle":0},{"time":0.3333,"angle":-15},{"time":0.4333,"angle":-30},{"time":0.6,"angle":25},{"time":0.7,"angle":45}],"translate":[{"time":0.2,"x":0,"y":0},{"time":0.3333,"x":-10,"y":20},{"time":0.4333,"x":-57.06,"y":27.17},{"time":0.7,"x":-113.89,"y":-8.36}],"scale":[{"time":0.2,"x":1,"y":1},{"time":0.7,"x":1,"y":0.3}]},"t2":{"rotate":[{"time":0.2667,"angle":5},{"time":0.3333,"angle":15},{"time":0.7,"angle":60}],"translate":[{"time":0.2667,"x":0,"y":0},{"time":0.3333,"x":5.47,"y":0},{"time":0.7,"x":-77.43,"y":78.35}],"scale":[{"time":0.2667,"x":1,"y":1},{"time":0.7,"x":0.3,"y":0.3}]},"t3":{"rotate":[{"time":0.2667,"angle":5},{"time":0.7,"angle":-60}],"translate":[{"time":0.2667,"x":0,"y":0},{"time":0.7,"x":9.66,"y":73.81}],"scale":[{"time":0.2667,"x":1,"y":1},{"time":0.7,"x":0.3,"y":0.3}],"shear":[{"time":0.2667,"x":0,"y":0},{"time":0.7,"x":-180,"y":0}]},"t1":{"rotate":[{"time":0.1,"angle":0},{"time":0.2,"angle":5.17}]},"water":{"scale":[{"time":0.1,"x":1,"y":1},{"time":0.7,"x":1.5,"y":1}]},"top":{"translate":[{"time":0.2,"x":0,"y":10}]},"lose":{"scale":[{"time":0.6333,"x":0.3,"y":0.3},{"time":0.7333,"x":1,"y":1}]}}},"action_lose2":{"slots":{"Wave":{"attachment":[{"time":0,"name":null}]},"bot1":{"color":[{"time":0,"color":"ffffff70","curve":"stepped"},{"time":0.6,"color":"ffffff70"},{"time":0.7,"color":"ffffff00"}],"attachment":[{"time":0,"name":null},{"time":0.1,"name":"explode ship/bot/bot 1"},{"time":0.7333,"name":null}]},"bot2":{"color":[{"time":0,"color":"ffffff70","curve":"stepped"},{"time":0.6,"color":"ffffff70"},{"time":0.7,"color":"ffffff00"}],"attachment":[{"time":0,"name":null},{"time":0.1,"name":"explode ship/bot/bot 2"},{"time":0.7333,"name":null}]},"bot3":{"color":[{"time":0,"color":"ffffff70","curve":"stepped"},{"time":0.6,"color":"ffffff70"},{"time":0.7,"color":"ffffff00"}],"attachment":[{"time":0,"name":null},{"time":0.1,"name":"explode ship/bot/bot 3"},{"time":0.7333,"name":null}]},"bot4":{"color":[{"time":0,"color":"ffffff70","curve":"stepped"},{"time":0.6,"color":"ffffff70"},{"time":0.7,"color":"ffffff00"}],"attachment":[{"time":0,"name":null},{"time":0.1,"name":"explode ship/bot/bot 4"},{"time":0.7333,"name":null}]},"bot5":{"color":[{"time":0,"color":"ffffff70","curve":"stepped"},{"time":0.6,"color":"ffffff70"},{"time":0.7,"color":"ffffff00"}],"attachment":[{"time":0,"name":null},{"time":0.1,"name":"explode ship/bot/bot 5"},{"time":0.7333,"name":null}]},"bot6":{"color":[{"time":0,"color":"ffffff70","curve":"stepped"},{"time":0.6,"color":"ffffff70"},{"time":0.7,"color":"ffffff00"}],"attachment":[{"time":0,"name":null},{"time":0.1,"name":"explode ship/bot/bot6"},{"time":0.7333,"name":null}]},"explode ship/water":{"color":[{"time":0,"color":"ffffff70"},{"time":0.6,"color":"ffffffff"},{"time":0.7,"color":"ffffff00"}],"attachment":[{"time":0,"name":null},{"time":0.1,"name":"explode ship/water"},{"time":0.7333,"name":null}]},"explode/2":{"color":[{"time":0,"color":"ffffff70","curve":"stepped"},{"time":0.6,"color":"ffffff70"},{"time":0.7,"color":"ffffff00"}],"attachment":[{"time":0.1,"name":"explode/2"},{"time":0.2,"name":"explode/3"},{"time":0.2667,"name":"explode/4"},{"time":0.3333,"name":"explode/5"},{"time":0.4333,"name":"explode/6"},{"time":0.5,"name":"explode/7"},{"time":0.6,"name":"explode/8"},{"time":0.7333,"name":null}]},"mid2":{"color":[{"time":0,"color":"ffffff70","curve":"stepped"},{"time":0.6,"color":"ffffff70"},{"time":0.7,"color":"ffffff00"}],"attachment":[{"time":0,"name":null},{"time":0.3333,"name":"explode ship/mid/mid 2"},{"time":0.7333,"name":null}]},"mid3":{"color":[{"time":0,"color":"ffffff70","curve":"stepped"},{"time":0.6,"color":"ffffff70"},{"time":0.7,"color":"ffffff00"}],"attachment":[{"time":0,"name":null},{"time":0.3333,"name":"explode ship/mid/mid 3"},{"time":0.7333,"name":null}]},"mid 1":{"color":[{"time":0,"color":"ffffff70"}],"attachment":[{"time":0,"name":null},{"time":0.1,"name":"explode ship/mid/mid 1"},{"time":0.3333,"name":null}]},"reasure & Skull/skull":{"color":[{"time":0,"color":"ffffff70"}],"attachment":[{"time":0.6333,"name":"treasure & Skull/skull"}]},"ship":{"attachment":[{"time":0,"name":null}]},"ship_outerglow":{"color":[{"time":0,"color":"ffffff70"}],"attachment":[{"time":0.1,"name":null}]},"top1":{"color":[{"time":0,"color":"ffffff70"}],"attachment":[{"time":0,"name":null},{"time":0.1,"name":"explode ship/top/top 1"},{"time":0.2667,"name":null}]},"top2":{"color":[{"time":0,"color":"ffffff70","curve":"stepped"},{"time":0.6,"color":"ffffff70"},{"time":0.7,"color":"ffffff00"}],"attachment":[{"time":0,"name":null},{"time":0.2667,"name":"explode ship/top/top2"},{"time":0.7333,"name":null}]},"top3":{"color":[{"time":0,"color":"ffffff70","curve":"stepped"},{"time":0.6,"color":"ffffff70"},{"time":0.7,"color":"ffffff00"}],"attachment":[{"time":0,"name":null},{"time":0.2667,"name":"explode ship/top/top3"},{"time":0.7333,"name":null}]}},"bones":{"explode":{"scale":[{"time":0.6,"x":1,"y":1},{"time":0.7,"x":1.2,"y":1.2}]},"b6":{"rotate":[{"time":0.1,"angle":0},{"time":0.4,"angle":107.62},{"time":0.6,"angle":-150}],"translate":[{"time":0.1,"x":0,"y":0},{"time":0.4,"x":-76.01,"y":-41.32},{"time":0.7,"x":-181.24,"y":-78.08}],"shear":[{"time":0.1,"x":0,"y":0},{"time":0.4,"x":90,"y":75},{"time":0.7,"x":0,"y":-180}]},"b1":{"rotate":[{"time":0.1,"angle":0},{"time":0.2667,"angle":15},{"time":0.3333,"angle":30},{"time":0.4333,"angle":45,"curve":"stepped"},{"time":0.6,"angle":45},{"time":0.7,"angle":60}],"translate":[{"time":0.1,"x":0,"y":0},{"time":0.2,"x":-19.1,"y":-0.5},{"time":0.2667,"x":-47.99,"y":-2.51},{"time":0.3333,"x":-77.12,"y":-6.42},{"time":0.4333,"x":-113.14,"y":-7.07},{"time":0.5,"x":-125.87,"y":-8.49,"curve":"stepped"},{"time":0.6,"x":-125.87,"y":-8.49},{"time":0.7,"x":-148.61,"y":-108.15}],"scale":[{"time":0.1,"x":1,"y":1},{"time":0.3333,"x":0.803,"y":1},{"time":0.5,"x":0.671,"y":1}],"shear":[{"time":0.3333,"x":0,"y":0},{"time":0.4333,"x":-143.64,"y":0},{"time":0.7,"x":-36.52,"y":0}]},"b2":{"rotate":[{"time":0.1,"angle":0},{"time":0.2,"angle":-5},{"time":0.2667,"angle":-30},{"time":0.3333,"angle":-60},{"time":0.4333,"angle":-75}],"translate":[{"time":0.1,"x":0,"y":0},{"time":0.2,"x":14.47,"y":4.76},{"time":0.2667,"x":89.95,"y":5.8},{"time":0.3333,"x":130.93,"y":-2.47},{"time":0.4333,"x":174.68,"y":-7.06},{"time":0.7,"x":175.92,"y":15.65}],"scale":[{"time":0.1,"x":1,"y":1},{"time":0.7,"x":0.5,"y":0.5}],"shear":[{"time":0.1,"x":0,"y":0},{"time":0.3333,"x":-180,"y":0},{"time":0.7,"x":135,"y":0}]},"b3":{"rotate":[{"time":0.1,"angle":0},{"time":0.2,"angle":-15},{"time":0.2667,"angle":-45},{"time":0.3333,"angle":-65}],"translate":[{"time":0.1,"x":0,"y":0},{"time":0.2,"x":17.59,"y":7.71},{"time":0.2667,"x":64.35,"y":12.02},{"time":0.3333,"x":113.09,"y":-3.54},{"time":0.4333,"x":133.51,"y":-9.46},{"time":0.5,"x":145.88,"y":-11.21},{"time":0.7,"x":125.81,"y":-40.42}],"scale":[{"time":0.1,"x":1,"y":1},{"time":0.7,"x":0.3,"y":0.3}]},"b4":{"rotate":[{"time":0.1,"angle":0},{"time":0.2667,"angle":12.07},{"time":0.6,"angle":75}],"translate":[{"time":0.1,"x":0.76,"y":1.52},{"time":0.7,"x":132.36,"y":-29.49}],"shear":[{"time":0.1,"x":0,"y":0},{"time":0.7,"x":145,"y":0}]},"b5":{"rotate":[{"time":0.4,"angle":0},{"time":0.6,"angle":-46.5}],"translate":[{"time":0.4,"x":0,"y":0},{"time":0.6,"x":50.92,"y":39.52},{"time":0.7,"x":72.24,"y":24.63}]},"m1":{"rotate":[{"time":0.2,"angle":5}],"translate":[{"time":0.2,"x":0,"y":8}]},"m2":{"rotate":[{"time":0.2,"angle":0},{"time":0.3333,"angle":15},{"time":0.4333,"angle":30},{"time":0.6,"angle":-54.02},{"time":0.7,"angle":-65}],"translate":[{"time":0.2,"x":0,"y":0},{"time":0.3333,"x":10,"y":20},{"time":0.4333,"x":45.88,"y":32.15},{"time":0.5,"x":61.14,"y":66.03},{"time":0.6,"x":90.06,"y":75.32},{"time":0.7,"x":117.51,"y":27.21}],"scale":[{"time":0.2,"x":1,"y":1},{"time":0.6,"x":1.5,"y":0.6}],"shear":[{"time":0.2,"x":0,"y":0},{"time":0.7,"x":0,"y":-45}]},"m3":{"rotate":[{"time":0.2,"angle":0},{"time":0.3333,"angle":-15},{"time":0.4333,"angle":-30},{"time":0.6,"angle":25},{"time":0.7,"angle":45}],"translate":[{"time":0.2,"x":0,"y":0},{"time":0.3333,"x":-10,"y":20},{"time":0.4333,"x":-57.06,"y":27.17},{"time":0.7,"x":-113.89,"y":-8.36}],"scale":[{"time":0.2,"x":1,"y":1},{"time":0.7,"x":1,"y":0.3}]},"t2":{"rotate":[{"time":0.2667,"angle":5},{"time":0.3333,"angle":15},{"time":0.7,"angle":60}],"translate":[{"time":0.2667,"x":0,"y":0},{"time":0.3333,"x":5.47,"y":0},{"time":0.7,"x":-77.43,"y":78.35}],"scale":[{"time":0.2667,"x":1,"y":1},{"time":0.7,"x":0.3,"y":0.3}]},"t3":{"rotate":[{"time":0.2667,"angle":5},{"time":0.7,"angle":-60}],"translate":[{"time":0.2667,"x":0,"y":0},{"time":0.7,"x":9.66,"y":73.81}],"scale":[{"time":0.2667,"x":1,"y":1},{"time":0.7,"x":0.3,"y":0.3}],"shear":[{"time":0.2667,"x":0,"y":0},{"time":0.7,"x":-180,"y":0}]},"t1":{"rotate":[{"time":0.1,"angle":0},{"time":0.2,"angle":5.17}]},"water":{"scale":[{"time":0.1,"x":1,"y":1},{"time":0.7,"x":1.5,"y":1}]},"top":{"translate":[{"time":0.2,"x":0,"y":10}]},"lose":{"scale":[{"time":0.6333,"x":0.3,"y":0.3},{"time":0.7333,"x":1,"y":1}]}}},"action_win":{"slots":{"Wave":{"attachment":[{"time":0,"name":null}]},"bot1":{"color":[{"time":0.6,"color":"ffffffff"},{"time":0.7,"color":"ffffff00"}],"attachment":[{"time":0,"name":null},{"time":0.1,"name":"explode ship/bot/bot 1"},{"time":0.7333,"name":null}]},"bot2":{"color":[{"time":0.6,"color":"ffffffff"},{"time":0.7,"color":"ffffff00"}],"attachment":[{"time":0,"name":null},{"time":0.1,"name":"explode ship/bot/bot 2"},{"time":0.7333,"name":null}]},"bot3":{"color":[{"time":0.6,"color":"ffffffff"},{"time":0.7,"color":"ffffff00"}],"attachment":[{"time":0,"name":null},{"time":0.1,"name":"explode ship/bot/bot 3"},{"time":0.7333,"name":null}]},"bot4":{"color":[{"time":0.6,"color":"ffffffff"},{"time":0.7,"color":"ffffff00"}],"attachment":[{"time":0,"name":null},{"time":0.1,"name":"explode ship/bot/bot 4"},{"time":0.7333,"name":null}]},"bot5":{"color":[{"time":0.6,"color":"ffffffff"},{"time":0.7,"color":"ffffff00"}],"attachment":[{"time":0,"name":null},{"time":0.1,"name":"explode ship/bot/bot 5"},{"time":0.7333,"name":null}]},"bot6":{"color":[{"time":0.6,"color":"ffffffff"},{"time":0.7,"color":"ffffff00"}],"attachment":[{"time":0,"name":null},{"time":0.1,"name":"explode ship/bot/bot6"},{"time":0.7333,"name":null}]},"explode ship/water":{"color":[{"time":0.6,"color":"ffffffff"},{"time":0.7,"color":"ffffff00"}],"attachment":[{"time":0,"name":null},{"time":0.1,"name":"explode ship/water"},{"time":0.7333,"name":null}]},"explode/2":{"color":[{"time":0.6,"color":"ffffffff"},{"time":0.7,"color":"ffffff00"}],"attachment":[{"time":0.1,"name":"explode/2"},{"time":0.2,"name":"explode/3"},{"time":0.2667,"name":"explode/4"},{"time":0.3333,"name":"explode/5"},{"time":0.4333,"name":"explode/6"},{"time":0.5,"name":"explode/7"},{"time":0.6,"name":"explode/8"},{"time":0.7333,"name":null}]},"mid2":{"color":[{"time":0.6,"color":"ffffffff"},{"time":0.7,"color":"ffffff00"}],"attachment":[{"time":0,"name":null},{"time":0.3333,"name":"explode ship/mid/mid 2"},{"time":0.7333,"name":null}]},"mid3":{"color":[{"time":0.6,"color":"ffffffff"},{"time":0.7,"color":"ffffff00"}],"attachment":[{"time":0,"name":null},{"time":0.3333,"name":"explode ship/mid/mid 3"},{"time":0.7333,"name":null}]},"mid 1":{"attachment":[{"time":0,"name":null},{"time":0.1,"name":"explode ship/mid/mid 1"},{"time":0.3333,"name":null}]},"reasure & Skull/light 101":{"attachment":[{"time":0.6333,"name":"treasure & Skull/light 100"}]},"ship":{"attachment":[{"time":0,"name":null}]},"ship_outerglow":{"attachment":[{"time":0.1,"name":null}]},"top1":{"attachment":[{"time":0,"name":null},{"time":0.1,"name":"explode ship/top/top 1"},{"time":0.2667,"name":null}]},"top2":{"color":[{"time":0.6,"color":"ffffffff"},{"time":0.7,"color":"ffffff00"}],"attachment":[{"time":0,"name":null},{"time":0.2667,"name":"explode ship/top/top2"},{"time":0.7333,"name":null}]},"top3":{"color":[{"time":0.6,"color":"ffffffff"},{"time":0.7,"color":"ffffff00"}],"attachment":[{"time":0,"name":null},{"time":0.2667,"name":"explode ship/top/top3"},{"time":0.7333,"name":null}]},"treasure & Skull/treasure":{"attachment":[{"time":0.6333,"name":"treasure & Skull/treasure"}]}},"bones":{"explode":{"scale":[{"time":0.6,"x":1,"y":1},{"time":0.7,"x":1.2,"y":1.2}]},"b6":{"rotate":[{"time":0.1,"angle":0},{"time":0.4,"angle":107.62},{"time":0.6,"angle":-150}],"translate":[{"time":0.1,"x":0,"y":0},{"time":0.4,"x":-76.01,"y":-41.32},{"time":0.7,"x":-181.24,"y":-78.08}],"shear":[{"time":0.1,"x":0,"y":0},{"time":0.4,"x":90,"y":75},{"time":0.7,"x":0,"y":-180}]},"b1":{"rotate":[{"time":0.1,"angle":0},{"time":0.2667,"angle":15},{"time":0.3333,"angle":30},{"time":0.4333,"angle":45,"curve":"stepped"},{"time":0.6,"angle":45},{"time":0.7,"angle":60}],"translate":[{"time":0.1,"x":0,"y":0},{"time":0.2,"x":-19.1,"y":-0.5},{"time":0.2667,"x":-47.99,"y":-2.51},{"time":0.3333,"x":-77.12,"y":-6.42},{"time":0.4333,"x":-113.14,"y":-7.07},{"time":0.5,"x":-125.87,"y":-8.49,"curve":"stepped"},{"time":0.6,"x":-125.87,"y":-8.49},{"time":0.7,"x":-148.61,"y":-108.15}],"scale":[{"time":0.1,"x":1,"y":1},{"time":0.3333,"x":0.803,"y":1},{"time":0.5,"x":0.671,"y":1}],"shear":[{"time":0.3333,"x":0,"y":0},{"time":0.4333,"x":-143.64,"y":0},{"time":0.7,"x":-36.52,"y":0}]},"b2":{"rotate":[{"time":0.1,"angle":0},{"time":0.2,"angle":-5},{"time":0.2667,"angle":-30},{"time":0.3333,"angle":-60},{"time":0.4333,"angle":-75}],"translate":[{"time":0.1,"x":0,"y":0},{"time":0.2,"x":14.47,"y":4.76},{"time":0.2667,"x":89.95,"y":5.8},{"time":0.3333,"x":130.93,"y":-2.47},{"time":0.4333,"x":174.68,"y":-7.06},{"time":0.7,"x":175.92,"y":15.65}],"scale":[{"time":0.1,"x":1,"y":1},{"time":0.7,"x":0.5,"y":0.5}],"shear":[{"time":0.1,"x":0,"y":0},{"time":0.3333,"x":-180,"y":0},{"time":0.7,"x":135,"y":0}]},"b3":{"rotate":[{"time":0.1,"angle":0},{"time":0.2,"angle":-15},{"time":0.2667,"angle":-45},{"time":0.3333,"angle":-65}],"translate":[{"time":0.1,"x":0,"y":0},{"time":0.2,"x":17.59,"y":7.71},{"time":0.2667,"x":64.35,"y":12.02},{"time":0.3333,"x":113.09,"y":-3.54},{"time":0.4333,"x":133.51,"y":-9.46},{"time":0.5,"x":145.88,"y":-11.21},{"time":0.7,"x":125.81,"y":-40.42}],"scale":[{"time":0.1,"x":1,"y":1},{"time":0.7,"x":0.3,"y":0.3}]},"b4":{"rotate":[{"time":0.1,"angle":0},{"time":0.2667,"angle":12.07},{"time":0.6,"angle":75}],"translate":[{"time":0.1,"x":0.76,"y":1.52},{"time":0.7,"x":132.36,"y":-29.49}],"shear":[{"time":0.1,"x":0,"y":0},{"time":0.7,"x":145,"y":0}]},"b5":{"rotate":[{"time":0.4,"angle":0},{"time":0.6,"angle":-46.5}],"translate":[{"time":0.4,"x":0,"y":0},{"time":0.6,"x":50.92,"y":39.52},{"time":0.7,"x":72.24,"y":24.63}]},"m1":{"rotate":[{"time":0.2,"angle":5}],"translate":[{"time":0.2,"x":0,"y":8}]},"m2":{"rotate":[{"time":0.2,"angle":0},{"time":0.3333,"angle":15},{"time":0.4333,"angle":30},{"time":0.6,"angle":-54.02},{"time":0.7,"angle":-65}],"translate":[{"time":0.2,"x":0,"y":0},{"time":0.3333,"x":10,"y":20},{"time":0.4333,"x":45.88,"y":32.15},{"time":0.5,"x":61.14,"y":66.03},{"time":0.6,"x":90.06,"y":75.32},{"time":0.7,"x":117.51,"y":27.21}],"scale":[{"time":0.2,"x":1,"y":1},{"time":0.6,"x":1.5,"y":0.6}],"shear":[{"time":0.2,"x":0,"y":0},{"time":0.7,"x":0,"y":-45}]},"m3":{"rotate":[{"time":0.2,"angle":0},{"time":0.3333,"angle":-15},{"time":0.4333,"angle":-30},{"time":0.6,"angle":25},{"time":0.7,"angle":45}],"translate":[{"time":0.2,"x":0,"y":0},{"time":0.3333,"x":-10,"y":20},{"time":0.4333,"x":-57.06,"y":27.17},{"time":0.7,"x":-113.89,"y":-8.36}],"scale":[{"time":0.2,"x":1,"y":1},{"time":0.7,"x":1,"y":0.3}]},"t2":{"rotate":[{"time":0.2667,"angle":5},{"time":0.3333,"angle":15},{"time":0.7,"angle":60}],"translate":[{"time":0.2667,"x":0,"y":0},{"time":0.3333,"x":5.47,"y":0},{"time":0.7,"x":-77.43,"y":78.35}],"scale":[{"time":0.2667,"x":1,"y":1},{"time":0.7,"x":0.3,"y":0.3}]},"t3":{"rotate":[{"time":0.2667,"angle":5},{"time":0.7,"angle":-60}],"translate":[{"time":0.2667,"x":0,"y":0},{"time":0.7,"x":9.66,"y":73.81}],"scale":[{"time":0.2667,"x":1,"y":1},{"time":0.7,"x":0.3,"y":0.3}],"shear":[{"time":0.2667,"x":0,"y":0},{"time":0.7,"x":-180,"y":0}]},"t1":{"rotate":[{"time":0.1,"angle":0},{"time":0.2,"angle":5.17}]},"water":{"scale":[{"time":0.1,"x":1,"y":1},{"time":0.7,"x":1.5,"y":1}]},"top":{"translate":[{"time":0.2,"x":0,"y":10}]},"Win":{"scale":[{"time":0.6333,"x":0.3,"y":0.3},{"time":0.7333,"x":1,"y":1}]},"light":{"scale":[{"time":0.6333,"x":0.3,"y":0.3},{"time":0.7333,"x":1,"y":1}]}}},"action_win2":{"slots":{"Wave":{"attachment":[{"time":0,"name":null}]},"bot1":{"color":[{"time":0,"color":"ffffff70","curve":"stepped"},{"time":0.6,"color":"ffffff70"},{"time":0.7,"color":"ffffff00"}],"attachment":[{"time":0,"name":null},{"time":0.1,"name":"explode ship/bot/bot 1"},{"time":0.7333,"name":null}]},"bot2":{"color":[{"time":0,"color":"ffffff70","curve":"stepped"},{"time":0.6,"color":"ffffff70"},{"time":0.7,"color":"ffffff00"}],"attachment":[{"time":0,"name":null},{"time":0.1,"name":"explode ship/bot/bot 2"},{"time":0.7333,"name":null}]},"bot3":{"color":[{"time":0,"color":"ffffff70","curve":"stepped"},{"time":0.6,"color":"ffffff70"},{"time":0.7,"color":"ffffff00"}],"attachment":[{"time":0,"name":null},{"time":0.1,"name":"explode ship/bot/bot 3"},{"time":0.7333,"name":null}]},"bot4":{"color":[{"time":0,"color":"ffffff70","curve":"stepped"},{"time":0.6,"color":"ffffff70"},{"time":0.7,"color":"ffffff00"}],"attachment":[{"time":0,"name":null},{"time":0.1,"name":"explode ship/bot/bot 4"},{"time":0.7333,"name":null}]},"bot5":{"color":[{"time":0,"color":"ffffff70","curve":"stepped"},{"time":0.6,"color":"ffffff70"},{"time":0.7,"color":"ffffff00"}],"attachment":[{"time":0,"name":null},{"time":0.1,"name":"explode ship/bot/bot 5"},{"time":0.7333,"name":null}]},"bot6":{"color":[{"time":0,"color":"ffffff70","curve":"stepped"},{"time":0.6,"color":"ffffff70"},{"time":0.7,"color":"ffffff00"}],"attachment":[{"time":0,"name":null},{"time":0.1,"name":"explode ship/bot/bot6"},{"time":0.7333,"name":null}]},"explode ship/water":{"color":[{"time":0,"color":"ffffff70","curve":"stepped"},{"time":0.6,"color":"ffffff70"},{"time":0.7,"color":"ffffff00"}],"attachment":[{"time":0,"name":null},{"time":0.1,"name":"explode ship/water"},{"time":0.7333,"name":null}]},"explode/2":{"color":[{"time":0,"color":"ffffff70","curve":"stepped"},{"time":0.6,"color":"ffffff70"},{"time":0.7,"color":"ffffff00"}],"attachment":[{"time":0.1,"name":"explode/2"},{"time":0.2,"name":"explode/3"},{"time":0.2667,"name":"explode/4"},{"time":0.3333,"name":"explode/5"},{"time":0.4333,"name":"explode/6"},{"time":0.5,"name":"explode/7"},{"time":0.6,"name":"explode/8"},{"time":0.7333,"name":null}]},"mid2":{"color":[{"time":0,"color":"ffffff70","curve":"stepped"},{"time":0.6,"color":"ffffff70"},{"time":0.7,"color":"ffffff00"}],"attachment":[{"time":0,"name":null},{"time":0.3333,"name":"explode ship/mid/mid 2"},{"time":0.7333,"name":null}]},"mid3":{"color":[{"time":0,"color":"ffffff70","curve":"stepped"},{"time":0.6,"color":"ffffff70"},{"time":0.7,"color":"ffffff00"}],"attachment":[{"time":0,"name":null},{"time":0.3333,"name":"explode ship/mid/mid 3"},{"time":0.7333,"name":null}]},"mid 1":{"color":[{"time":0,"color":"ffffff70"}],"attachment":[{"time":0,"name":null},{"time":0.1,"name":"explode ship/mid/mid 1"},{"time":0.3333,"name":null}]},"reasure & Skull/light 101":{"color":[{"time":0,"color":"ffffff70"}],"attachment":[{"time":0.6333,"name":"treasure & Skull/light 100"}]},"ship":{"attachment":[{"time":0,"name":null}]},"ship_outerglow":{"color":[{"time":0,"color":"ffffff70"}],"attachment":[{"time":0.1,"name":null}]},"top1":{"color":[{"time":0,"color":"ffffff70"}],"attachment":[{"time":0,"name":null},{"time":0.1,"name":"explode ship/top/top 1"},{"time":0.2667,"name":null}]},"top2":{"color":[{"time":0,"color":"ffffff70","curve":"stepped"},{"time":0.6,"color":"ffffff70"},{"time":0.7,"color":"ffffff00"}],"attachment":[{"time":0,"name":null},{"time":0.2667,"name":"explode ship/top/top2"},{"time":0.7333,"name":null}]},"top3":{"color":[{"time":0,"color":"ffffff70","curve":"stepped"},{"time":0.6,"color":"ffffff70"},{"time":0.7,"color":"ffffff00"}],"attachment":[{"time":0,"name":null},{"time":0.2667,"name":"explode ship/top/top3"},{"time":0.7333,"name":null}]},"treasure & Skull/treasure":{"color":[{"time":0,"color":"ffffff70"}],"attachment":[{"time":0.6333,"name":"treasure & Skull/treasure"}]}},"bones":{"explode":{"scale":[{"time":0.6,"x":1,"y":1},{"time":0.7,"x":1.2,"y":1.2}]},"b6":{"rotate":[{"time":0.1,"angle":0},{"time":0.4,"angle":107.62},{"time":0.6,"angle":-150}],"translate":[{"time":0.1,"x":0,"y":0},{"time":0.4,"x":-76.01,"y":-41.32},{"time":0.7,"x":-181.24,"y":-78.08}],"shear":[{"time":0.1,"x":0,"y":0},{"time":0.4,"x":90,"y":75},{"time":0.7,"x":0,"y":-180}]},"b1":{"rotate":[{"time":0.1,"angle":0},{"time":0.2667,"angle":15},{"time":0.3333,"angle":30},{"time":0.4333,"angle":45,"curve":"stepped"},{"time":0.6,"angle":45},{"time":0.7,"angle":60}],"translate":[{"time":0.1,"x":0,"y":0},{"time":0.2,"x":-19.1,"y":-0.5},{"time":0.2667,"x":-47.99,"y":-2.51},{"time":0.3333,"x":-77.12,"y":-6.42},{"time":0.4333,"x":-113.14,"y":-7.07},{"time":0.5,"x":-125.87,"y":-8.49,"curve":"stepped"},{"time":0.6,"x":-125.87,"y":-8.49},{"time":0.7,"x":-148.61,"y":-108.15}],"scale":[{"time":0.1,"x":1,"y":1},{"time":0.3333,"x":0.803,"y":1},{"time":0.5,"x":0.671,"y":1}],"shear":[{"time":0.3333,"x":0,"y":0},{"time":0.4333,"x":-143.64,"y":0},{"time":0.7,"x":-36.52,"y":0}]},"b2":{"rotate":[{"time":0.1,"angle":0},{"time":0.2,"angle":-5},{"time":0.2667,"angle":-30},{"time":0.3333,"angle":-60},{"time":0.4333,"angle":-75}],"translate":[{"time":0.1,"x":0,"y":0},{"time":0.2,"x":14.47,"y":4.76},{"time":0.2667,"x":89.95,"y":5.8},{"time":0.3333,"x":130.93,"y":-2.47},{"time":0.4333,"x":174.68,"y":-7.06},{"time":0.7,"x":175.92,"y":15.65}],"scale":[{"time":0.1,"x":1,"y":1},{"time":0.7,"x":0.5,"y":0.5}],"shear":[{"time":0.1,"x":0,"y":0},{"time":0.3333,"x":-180,"y":0},{"time":0.7,"x":135,"y":0}]},"b3":{"rotate":[{"time":0.1,"angle":0},{"time":0.2,"angle":-15},{"time":0.2667,"angle":-45},{"time":0.3333,"angle":-65}],"translate":[{"time":0.1,"x":0,"y":0},{"time":0.2,"x":17.59,"y":7.71},{"time":0.2667,"x":64.35,"y":12.02},{"time":0.3333,"x":113.09,"y":-3.54},{"time":0.4333,"x":133.51,"y":-9.46},{"time":0.5,"x":145.88,"y":-11.21},{"time":0.7,"x":125.81,"y":-40.42}],"scale":[{"time":0.1,"x":1,"y":1},{"time":0.7,"x":0.3,"y":0.3}]},"b4":{"rotate":[{"time":0.1,"angle":0},{"time":0.2667,"angle":12.07},{"time":0.6,"angle":75}],"translate":[{"time":0.1,"x":0.76,"y":1.52},{"time":0.7,"x":132.36,"y":-29.49}],"shear":[{"time":0.1,"x":0,"y":0},{"time":0.7,"x":145,"y":0}]},"b5":{"rotate":[{"time":0.4,"angle":0},{"time":0.6,"angle":-46.5}],"translate":[{"time":0.4,"x":0,"y":0},{"time":0.6,"x":50.92,"y":39.52},{"time":0.7,"x":72.24,"y":24.63}]},"m1":{"rotate":[{"time":0.2,"angle":5}],"translate":[{"time":0.2,"x":0,"y":8}]},"m2":{"rotate":[{"time":0.2,"angle":0},{"time":0.3333,"angle":15},{"time":0.4333,"angle":30},{"time":0.6,"angle":-54.02},{"time":0.7,"angle":-65}],"translate":[{"time":0.2,"x":0,"y":0},{"time":0.3333,"x":10,"y":20},{"time":0.4333,"x":45.88,"y":32.15},{"time":0.5,"x":61.14,"y":66.03},{"time":0.6,"x":90.06,"y":75.32},{"time":0.7,"x":117.51,"y":27.21}],"scale":[{"time":0.2,"x":1,"y":1},{"time":0.6,"x":1.5,"y":0.6}],"shear":[{"time":0.2,"x":0,"y":0},{"time":0.7,"x":0,"y":-45}]},"m3":{"rotate":[{"time":0.2,"angle":0},{"time":0.3333,"angle":-15},{"time":0.4333,"angle":-30},{"time":0.6,"angle":25},{"time":0.7,"angle":45}],"translate":[{"time":0.2,"x":0,"y":0},{"time":0.3333,"x":-10,"y":20},{"time":0.4333,"x":-57.06,"y":27.17},{"time":0.7,"x":-113.89,"y":-8.36}],"scale":[{"time":0.2,"x":1,"y":1},{"time":0.7,"x":1,"y":0.3}]},"t2":{"rotate":[{"time":0.2667,"angle":5},{"time":0.3333,"angle":15},{"time":0.7,"angle":60}],"translate":[{"time":0.2667,"x":0,"y":0},{"time":0.3333,"x":5.47,"y":0},{"time":0.7,"x":-77.43,"y":78.35}],"scale":[{"time":0.2667,"x":1,"y":1},{"time":0.7,"x":0.3,"y":0.3}]},"t3":{"rotate":[{"time":0.2667,"angle":5},{"time":0.7,"angle":-60}],"translate":[{"time":0.2667,"x":0,"y":0},{"time":0.7,"x":9.66,"y":73.81}],"scale":[{"time":0.2667,"x":1,"y":1},{"time":0.7,"x":0.3,"y":0.3}],"shear":[{"time":0.2667,"x":0,"y":0},{"time":0.7,"x":-180,"y":0}]},"t1":{"rotate":[{"time":0.1,"angle":0},{"time":0.2,"angle":5.17}]},"water":{"scale":[{"time":0.1,"x":1,"y":1},{"time":0.7,"x":1.5,"y":1}]},"top":{"translate":[{"time":0.2,"x":0,"y":10}]},"Win":{"scale":[{"time":0.6333,"x":0.3,"y":0.3},{"time":0.7333,"x":1,"y":1}]},"light":{"scale":[{"time":0.6333,"x":0.3,"y":0.3},{"time":0.7333,"x":1,"y":1}]}}},"idle":{"slots":{"Wave":{"attachment":[{"time":0.4333,"name":null},{"time":1.4667,"name":"wave/1"}]},"bot1":{"attachment":[{"time":0,"name":null}]},"bot2":{"attachment":[{"time":0,"name":null}]},"bot3":{"attachment":[{"time":0,"name":null}]},"bot4":{"attachment":[{"time":0,"name":null}]},"bot5":{"attachment":[{"time":0,"name":null}]},"bot6":{"attachment":[{"time":0,"name":null}]},"explode ship/water":{"attachment":[{"time":0,"name":null}]},"mid2":{"attachment":[{"time":0,"name":null}]},"mid3":{"attachment":[{"time":0,"name":null}]},"mid 1":{"attachment":[{"time":0,"name":null}]},"ship_outerglow":{"attachment":[{"time":0,"name":null}]},"top1":{"attachment":[{"time":0,"name":null}]},"top2":{"attachment":[{"time":0,"name":null}]},"top3":{"attachment":[{"time":0,"name":null}]},"wave/1":{"attachment":[{"time":0.4333,"name":"wave/2"},{"time":0.5333,"name":null}]},"wave/2":{"attachment":[{"time":0.5333,"name":"wave/3"},{"time":0.7,"name":null}]},"wave/3":{"attachment":[{"time":0.7,"name":"wave/4"},{"time":0.8333,"name":null}]},"wave/4":{"attachment":[{"time":0.8333,"name":"wave/5"},{"time":1,"name":null}]},"wave/6":{"attachment":[{"time":1,"name":"wave/6"},{"time":1.1,"name":null}]},"wave/7":{"attachment":[{"time":1.1,"name":"wave/7"},{"time":1.2667,"name":null}]},"wave/8":{"attachment":[{"time":1.2667,"name":"wave/8"},{"time":1.3667,"name":null}]},"wave/9":{"attachment":[{"time":1.3667,"name":"wave/9"},{"time":1.4667,"name":null}]}},"bones":{"ship":{"rotate":[{"time":0,"angle":0},{"time":0.5,"angle":-8},{"time":0.8333,"angle":5},{"time":1.5,"angle":0}],"translate":[{"time":0,"x":0,"y":0},{"time":0.8333,"x":-1.11,"y":-7.92},{"time":1.5,"x":0,"y":0}]},"Wave":{"scale":[{"time":0,"x":1,"y":1},{"time":0.1667,"x":1.1,"y":1,"curve":"stepped"},{"time":0.2667,"x":1.1,"y":1},{"time":1.3667,"x":1,"y":1}]}}},"lose":{"slots":{"Wave":{"attachment":[{"time":0,"name":null}]},"bot1":{"attachment":[{"time":0,"name":null}]},"bot2":{"attachment":[{"time":0,"name":null}]},"bot3":{"attachment":[{"time":0,"name":null}]},"bot4":{"attachment":[{"time":0,"name":null}]},"bot5":{"attachment":[{"time":0,"name":null}]},"bot6":{"attachment":[{"time":0,"name":null}]},"explode ship/water":{"attachment":[{"time":0,"name":null}]},"mid2":{"attachment":[{"time":0,"name":null}]},"mid3":{"attachment":[{"time":0,"name":null}]},"mid 1":{"attachment":[{"time":0,"name":null}]},"reasure & Skull/skull":{"attachment":[{"time":0,"name":"treasure & Skull/skull"}]},"ship":{"attachment":[{"time":0,"name":null}]},"ship_outerglow":{"attachment":[{"time":0,"name":null}]},"top1":{"attachment":[{"time":0,"name":null}]},"top2":{"attachment":[{"time":0,"name":null}]},"top3":{"attachment":[{"time":0,"name":null}]}},"bones":{"Result":{"scale":[{"time":0,"x":1,"y":1},{"time":0.5,"x":1.2,"y":1.2},{"time":1,"x":1,"y":1},{"time":1.5,"x":1.2,"y":1.2},{"time":2,"x":1,"y":1}]}}},"lose2":{"slots":{"Wave":{"attachment":[{"time":0,"name":null}]},"bot1":{"attachment":[{"time":0,"name":null}]},"bot2":{"attachment":[{"time":0,"name":null}]},"bot3":{"attachment":[{"time":0,"name":null}]},"bot4":{"attachment":[{"time":0,"name":null}]},"bot5":{"attachment":[{"time":0,"name":null}]},"bot6":{"attachment":[{"time":0,"name":null}]},"explode ship/water":{"attachment":[{"time":0,"name":null}]},"mid2":{"attachment":[{"time":0,"name":null}]},"mid3":{"attachment":[{"time":0,"name":null}]},"mid 1":{"attachment":[{"time":0,"name":null}]},"reasure & Skull/skull":{"color":[{"time":0,"color":"ffffff70"}],"attachment":[{"time":0,"name":"treasure & Skull/skull"}]},"ship":{"attachment":[{"time":0,"name":null}]},"ship_outerglow":{"attachment":[{"time":0,"name":null}]},"top1":{"attachment":[{"time":0,"name":null}]},"top2":{"attachment":[{"time":0,"name":null}]},"top3":{"attachment":[{"time":0,"name":null}]}},"bones":{"Result":{"scale":[{"time":0,"x":1,"y":1},{"time":0.5,"x":1.2,"y":1.2},{"time":1,"x":1,"y":1},{"time":1.5,"x":1.2,"y":1.2},{"time":2,"x":1,"y":1}]}}},"win":{"slots":{"Wave":{"attachment":[{"time":0,"name":null}]},"bot1":{"attachment":[{"time":0,"name":null}]},"bot2":{"attachment":[{"time":0,"name":null}]},"bot3":{"attachment":[{"time":0,"name":null}]},"bot4":{"attachment":[{"time":0,"name":null}]},"bot5":{"attachment":[{"time":0,"name":null}]},"bot6":{"attachment":[{"time":0,"name":null}]},"explode ship/water":{"attachment":[{"time":0,"name":null}]},"mid2":{"attachment":[{"time":0,"name":null}]},"mid3":{"attachment":[{"time":0,"name":null}]},"mid 1":{"attachment":[{"time":0,"name":null}]},"reasure & Skull/light 101":{"attachment":[{"time":0,"name":"treasure & Skull/light 100"}]},"ship":{"attachment":[{"time":0,"name":null}]},"ship_outerglow":{"attachment":[{"time":0,"name":null}]},"top1":{"attachment":[{"time":0,"name":null}]},"top2":{"attachment":[{"time":0,"name":null}]},"top3":{"attachment":[{"time":0,"name":null}]},"treasure & Skull/treasure":{"attachment":[{"time":0,"name":"treasure & Skull/treasure"}]}},"bones":{"Result":{"scale":[{"time":0,"x":1,"y":1},{"time":0.5,"x":1.2,"y":1.2},{"time":1,"x":1,"y":1},{"time":1.5,"x":1.2,"y":1.2},{"time":2,"x":1,"y":1}]},"light":{"rotate":[{"time":0,"angle":0},{"time":0.3333,"angle":-90},{"time":0.6667,"angle":180},{"time":1,"angle":90},{"time":1.3333,"angle":-90},{"time":1.6667,"angle":180},{"time":2,"angle":90}]}}},"win2":{"slots":{"Wave":{"attachment":[{"time":0,"name":null}]},"bot1":{"attachment":[{"time":0,"name":null}]},"bot2":{"attachment":[{"time":0,"name":null}]},"bot3":{"attachment":[{"time":0,"name":null}]},"bot4":{"attachment":[{"time":0,"name":null}]},"bot5":{"attachment":[{"time":0,"name":null}]},"bot6":{"attachment":[{"time":0,"name":null}]},"explode ship/water":{"attachment":[{"time":0,"name":null}]},"mid2":{"attachment":[{"time":0,"name":null}]},"mid3":{"attachment":[{"time":0,"name":null}]},"mid 1":{"attachment":[{"time":0,"name":null}]},"reasure & Skull/skull":{"color":[{"time":0,"color":"ffffff70"}]},"ship":{"attachment":[{"time":0,"name":null}]},"ship_outerglow":{"attachment":[{"time":0,"name":null}]},"top1":{"attachment":[{"time":0,"name":null}]},"top2":{"attachment":[{"time":0,"name":null}]},"top3":{"attachment":[{"time":0,"name":null}]},"treasure & Skull/treasure":{"color":[{"time":0,"color":"ffffff70"}],"attachment":[{"time":0,"name":"treasure & Skull/treasure"}]}},"bones":{"Result":{"scale":[{"time":0,"x":1,"y":1},{"time":0.5,"x":1.2,"y":1.2},{"time":1,"x":1,"y":1},{"time":1.5,"x":1.2,"y":1.2},{"time":2,"x":1,"y":1}]}}}}}