{"skeleton":{"hash":"0H0TsLow9nWJlPSeGsreiEfdbCc","spine":"3.7.94","width":294,"height":292,"images":"","audio":""},"bones":[{"name":"root"},{"name":"bone","parent":"root"},{"name":"bone2","parent":"root"},{"name":"bone3","parent":"root"},{"name":"bone4","parent":"bone"},{"name":"bone5","parent":"root"},{"name":"bone6","parent":"root"},{"name":"bone7","parent":"root"}],"slots":[{"name":"Layer 35","bone":"bone","attachment":"Layer 35"},{"name":"Layer 36","bone":"bone4","attachment":"Layer 49"},{"name":"Layer 49","bone":"bone4","attachment":"Layer 50"},{"name":"Layer-35_0003_Layer-45","bone":"bone2","attachment":"Layer-35_0003_Layer-45"},{"name":"GIỮ ĐỂ TỰ QUAY","bone":"bone3","attachment":"GIỮ ĐỂ TỰ QUAY"},{"name":"Dừng","bone":"bone5","attachment":"Dừng"},{"name":"35_bac","bone":"bone6","attachment":"35_bac"},{"name":"Layer 36_bac","bone":"bone7","attachment":"Layer 36_bac"}],"skins":{"default":{"35_bac":{"35_bac":{"width":206,"height":208}},"Dừng":{"Dừng":{"x":0.5,"width":111,"height":41}},"GIỮ ĐỂ TỰ QUAY":{"GIỮ ĐỂ TỰ QUAY":{"x":0.5,"y":0.5,"width":155,"height":73}},"Layer 35":{"Layer 35":{"width":206,"height":208}},"Layer 36":{"Layer 49":{"width":202,"height":208}},"Layer 36_bac":{"Layer 36_bac":{"width":206,"height":208}},"Layer 49":{"Layer 50":{"width":294,"height":292}},"Layer-35_0003_Layer-45":{"Layer-35_0003_Layer-45":{"width":206,"height":208}}}},"animations":{"stop_disable":{"slots":{"35_bac":{"attachment":[{"time":0,"name":null}]},"GIỮ ĐỂ TỰ QUAY":{"attachment":[{"time":0,"name":null}]},"Layer 35":{"color":[{"time":0,"color":"818181ff"}]},"Layer 36":{"attachment":[{"time":0,"name":null}]},"Layer 36_bac":{"attachment":[{"time":0,"name":null}]},"Layer 49":{"attachment":[{"time":0,"name":null}]},"Layer-35_0003_Layer-45":{"color":[{"time":0,"color":"7e7e7eff"}]}},"bones":{"bone2":{"rotate":[{"time":0,"angle":0},{"time":5,"angle":90},{"time":10,"angle":180},{"time":14.9333,"angle":-90},{"time":19.9333,"angle":0}]},"bone":{"rotate":[{"time":0,"angle":0},{"time":10.0667,"angle":180},{"time":19.9,"angle":0}]},"bone3":{"translate":[{"time":0,"x":0.82,"y":-17.6}]},"bone5":{"translate":[{"time":0,"x":3.3,"y":0}],"scale":[{"time":0,"x":1.1,"y":1.1}]}}},"stop":{"slots":{"35_bac":{"attachment":[{"time":0,"name":null}]},"GIỮ ĐỂ TỰ QUAY":{"attachment":[{"time":0,"name":null}]},"Layer 36":{"attachment":[{"time":0,"name":null}]},"Layer 36_bac":{"attachment":[{"time":0,"name":null}]},"Layer 49":{"attachment":[{"time":0,"name":null}]}},"bones":{"bone2":{"rotate":[{"time":0,"angle":0},{"time":5,"angle":90},{"time":10,"angle":180},{"time":14.9333,"angle":-90},{"time":19.9333,"angle":0}]},"bone":{"rotate":[{"time":0,"angle":0},{"time":10.0667,"angle":180},{"time":19.9,"angle":0}]},"bone3":{"translate":[{"time":0,"x":0.82,"y":-17.6}]},"bone5":{"translate":[{"time":0,"x":3.3,"y":0},{"time":14.5,"x":0,"y":0.82}],"scale":[{"time":0,"x":1.1,"y":1.1}]}}},"spin":{"slots":{"35_bac":{"attachment":[{"time":0,"name":null}]},"Dừng":{"attachment":[{"time":0,"name":null}]},"Layer 36":{"attachment":[{"time":0,"name":null}]},"Layer 36_bac":{"attachment":[{"time":0,"name":null}]},"Layer 49":{"attachment":[{"time":0,"name":null}]}},"bones":{"bone2":{"rotate":[{"time":0,"angle":0},{"time":5,"angle":90},{"time":10,"angle":180},{"time":14.9333,"angle":-90},{"time":19.9333,"angle":0}]},"bone":{"rotate":[{"time":0,"angle":0},{"time":10.0667,"angle":180},{"time":19.9,"angle":0}]},"bone3":{"translate":[{"time":0,"x":0.82,"y":-17.6}]}}},"hold":{"slots":{"35_bac":{"attachment":[{"time":0,"name":null}]},"Dừng":{"attachment":[{"time":0,"name":null}]},"Layer 36":{"color":[{"time":0.1667,"color":"ffffff00"},{"time":0.3333,"color":"ffffffff"}],"attachment":[{"time":0,"name":null},{"time":0.1667,"name":"Layer 49"}]},"Layer 36_bac":{"attachment":[{"time":0,"name":null}]},"Layer 49":{"color":[{"time":0.6667,"color":"ffffff00"},{"time":1,"color":"ffffffff"}],"attachment":[{"time":0,"name":null},{"time":0.6667,"name":"Layer 50"}]}},"bones":{"bone2":{"rotate":[{"time":0,"angle":0},{"time":0.1667,"angle":90},{"time":0.3333,"angle":180},{"time":0.5,"angle":-90},{"time":0.6667,"angle":0},{"time":0.8,"angle":90},{"time":0.9333,"angle":180},{"time":1.0667,"angle":-90},{"time":1.2,"angle":0},{"time":1.2667,"angle":90},{"time":1.3333,"angle":180},{"time":1.4,"angle":-90},{"time":1.4667,"angle":0},{"time":1.5333,"angle":90},{"time":1.6,"angle":180},{"time":1.6667,"angle":-90},{"time":1.7333,"angle":0},{"time":1.8,"angle":90},{"time":1.8667,"angle":180},{"time":1.9333,"angle":-90},{"time":2,"angle":0}]},"bone":{"rotate":[{"time":0,"angle":0},{"time":0.3333,"angle":180},{"time":0.6667,"angle":0},{"time":0.9333,"angle":180},{"time":1.1333,"angle":0},{"time":1.3333,"angle":180},{"time":1.5333,"angle":0},{"time":1.6667,"angle":180},{"time":1.8,"angle":0},{"time":1.9333,"angle":180},{"time":2,"angle":0}]},"bone3":{"translate":[{"time":0,"x":0.82,"y":-17.6}]}}}}}
