{"skeleton":{"hash":"0NWX8AhTNX7scrngqTyGazdg6jc","spine":"3.7.94","width":266,"height":425.5,"images":"./New Folder With Items/Icon games/spine/Pirate_KIng/","audio":"/Users/dat09/Desktop"},"bones":[{"name":"root"},{"name":"BG","parent":"root"},{"name":"bone4","parent":"root","x":1.04,"y":-62.4},{"name":"bone5","parent":"root","y":23},{"name":"bone6","parent":"root","y":-65},{"name":"bone","parent":"root","y":-153},{"name":"bone2","parent":"bone5","x":-1,"y":-50},{"name":"bone3","parent":"bone5","x":2,"y":100},{"name":"bone7","parent":"bone5","x":13},{"name":"bone8","parent":"bone7","length":87.19,"rotation":18.78,"x":-71.3,"y":-25.01}],"slots":[{"name":"BG","bone":"BG","attachment":"BG"},{"name":"MAIN","bone":"bone2","attachment":"body"},{"name":"Treasure","bone":"bone4","attachment":"spark","blend":"additive"},{"name":"jackpot pool","bone":"bone","attachment":"jackpot pool"},{"name":"named","bone":"bone6","attachment":"named"},{"name":"Head","bone":"bone3","attachment":"Head"},{"name":"hand","bone":"bone8","attachment":"hand"}],"skins":{"default":{"BG":{"BG":{"y":0.5,"width":266,"height":420}},"Head":{"Head":{"x":0.5,"y":0.5,"width":183,"height":137}},"MAIN":{"body":{"y":0.5,"width":262,"height":358}},"Treasure":{"spark":{"y":50,"width":257,"height":364}},"hand":{"hand":{"x":75.71,"y":1.2,"rotation":-18.78,"width":122,"height":107}},"jackpot pool":{"jackpot pool":{"y":-3,"width":265,"height":118}},"named":{"named":{"y":0.5,"width":258,"height":72}}}},"animations":{"animation":{"bones":{"bone5":{"translate":[{"time":0,"x":0,"y":0},{"time":1,"x":0,"y":7},{"time":2,"x":0,"y":0}],"scale":[{"time":0,"x":1,"y":1},{"time":1,"x":1.05,"y":1.05},{"time":2,"x":1,"y":1}]},"bone4":{"scale":[{"time":0,"x":1,"y":1},{"time":1,"x":1.1,"y":1.1},{"time":2,"x":1,"y":1}]},"bone6":{"scale":[{"time":0,"x":1,"y":1},{"time":1,"x":1.2,"y":1.2},{"time":2,"x":1,"y":1}]},"bone3":{"translate":[{"time":0,"x":0,"y":0},{"time":1,"x":0,"y":-3},{"time":2,"x":0,"y":0}]},"bone8":{"rotate":[{"time":0,"angle":0},{"time":1,"angle":-5.69},{"time":2,"angle":0}]}}}}}